{
  "type": "farmersdelight:cooking",
  "ingredients": [
    {
      "item": "ends_delight:shulker_meat"
    },
    {
      "item": "minecraft:chorus_fruit"
    },
    {
      "item": "ends_delight:chorus_succulent"
    },
    {
      "item": "ends_delight:chorus_succulent"
    },
    {
      "tag": "forge:crops/tomato"
    },
    {
      "item": "farmersdelight:onion"
    }
  ],
  "result": {
    "item": "ends_delight:grilled_shulker_block"
  },
  "cookingtime": 200
}
